dmDjango/__init__.py
dmDjango/base.py
dmDjango/client.py
dmDjango/compiler.py
dmDjango/creation.py
dmDjango/features.py
dmDjango/introspection.py
dmDjango/operations.py
dmDjango/schema.py
dmDjango/utils.py
dmDjango/validation.py
dmDjango-3.0.3.dist-info/LICENSE.txt
dmDjango-3.0.3.dist-info/METADATA
dmDjango-3.0.3.dist-info/WHEEL
dmDjango-3.0.3.dist-info/top_level.txt
dmDjango-3.0.3.dist-info/RECORD
