Metadata-Version: 2.1
Name: dmDjango
Version: 3.0.3
Summary: Dameng database backend for Django
Home-page: https://eco.dameng.com/download/
Author: Dameng
Author-email: 
License-File: LICENSE.txt
